linien_gui/__init__.py
linien_gui/app.py
linien_gui/config.py
linien_gui/dialogs.py
linien_gui/icon.ico
linien_gui/threads.py
linien_gui/utils.py
linien_gui/ui/__init__.py
linien_gui/ui/device_manager.py
linien_gui/ui/device_manager.ui
linien_gui/ui/general_panel.py
linien_gui/ui/general_panel.ui
linien_gui/ui/lock_status_panel.py
linien_gui/ui/locking_panel.py
linien_gui/ui/locking_panel.ui
linien_gui/ui/logging_panel.py
linien_gui/ui/logging_panel.ui
linien_gui/ui/main_window.py
linien_gui/ui/main_window.ui
linien_gui/ui/modulation_sweep_panel.py
linien_gui/ui/modulation_sweep_panel.ui
linien_gui/ui/new_device_dialog.py
linien_gui/ui/new_device_dialog.ui
linien_gui/ui/optimization_panel.py
linien_gui/ui/optimization_panel.ui
linien_gui/ui/plot_widget.py
linien_gui/ui/psd_plot_widget.py
linien_gui/ui/psd_table_widget.py
linien_gui/ui/psd_window.py
linien_gui/ui/psd_window.ui
linien_gui/ui/right_panel.py
linien_gui/ui/spectroscopy_panel.py
linien_gui/ui/spectroscopy_panel.ui
linien_gui/ui/spin_box.py
linien_gui/ui/sweep_control.py
linien_gui/ui/version_checker.py
linien_gui/ui/view_panel.py
linien_gui/ui/view_panel.ui
linien_gui-2.1.0.dist-info/METADATA
linien_gui-2.1.0.dist-info/WHEEL
linien_gui-2.1.0.dist-info/entry_points.txt
linien_gui-2.1.0.dist-info/top_level.txt
linien_gui-2.1.0.dist-info/RECORD
