Metadata-Version: 2.1
Name: linien-gui
Version: 2.1.0
Summary: Graphical user interface of the Linien spectroscopy lock application.
Author-email: Benjamin Wiegand <benjamin.wiegand@physik.hu-berlin.de>, Bastian Leykauf <leykauf@physik.hu-berlin.de>, Robert Jördens <rj@quartiq.de>, Christian Freier <christian.freier@gmail.com>, Doron Behar <doron.behar@gmail.com>
Maintainer-email: Bastian Leykauf <leykauf@physik.hu-berlin.de>
Project-URL: Homepage, https://github.com/linien-org/linien
Classifier: Programming Language :: Python :: 3
Classifier: License :: OSI Approved :: GNU General Public License v3 (GPLv3)
Classifier: Operating System :: OS Independent
Requires-Python: >=3.8
Requires-Dist: click <9.0,>=8.1.7
Requires-Dist: pyqtgraph >=0.10.0
Requires-Dist: PyQt5 <6.0,>=5.12.0
Requires-Dist: requests <3.0,>=2.31.0
Requires-Dist: superqt >=0.2.3
Requires-Dist: linien-client ==2.1.0
